README.md
setup.py
flask_dino_utils/__init__.py
flask_dino_utils/authenticators.py
flask_dino_utils/filtering.py
flask_dino_utils/pagination.py
flask_dino_utils/sorting.py
flask_dino_utils/validators.py
flask_dino_utils/views.py
flask_dino_utils.egg-info/PKG-INFO
flask_dino_utils.egg-info/SOURCES.txt
flask_dino_utils.egg-info/dependency_links.txt
flask_dino_utils.egg-info/requires.txt
flask_dino_utils.egg-info/top_level.txt