Metadata-Version: 1.0
Name: flask-dino-utils
Version: 0.1.15
Summary: Flask utils package to use it among with Flask-Classy and marshmallow
Home-page: http://github.com/dinocloud/flask-dino-utils
Author: DinoCloud
Author-email: info@dinocloudconsulting.com
License: MIT
Platform: UNKNOWN
